{
  "CP-38-CR-0000745-2019": {
    "assignmentID": "cp0h2h09check4",
    "position": {
      "index": 0,
      "page": 0
    },
    "id": "CP-38-CR-0000745-2019",
    "filingDate": "4/25/2019 1:55:00 PM",
    "foundTimestamp": 1564056218781
  },
  "CP-23-CR-0000257-2019": {
    "assignmentID": "cp0h2h09check4",
    "position": {
      "index": 0,
      "page": 0
    },
    "id": "CP-23-CR-0000257-2019",
    "filingDate": "1/18/2019 3:03:00 PM",
    "foundTimestamp": 1564056218901
  },
  "CP-45-CR-0001946-2018": {
    "assignmentID": "cp0h2h09check4",
    "position": {
      "index": 0,
      "page": 0
    },
    "id": "CP-45-CR-0001946-2018",
    "filingDate": "9/4/2018 8:41:00 AM",
    "foundTimestamp": 1564056218943
  },
  "CP-39-CR-0003266-2018": {
    "assignmentID": "cp0h2h09check4",
    "position": {
      "index": 0,
      "page": 0
    },
    "id": "CP-39-CR-0003266-2018",
    "filingDate": "7/31/2018 10:55:00 AM",
    "foundTimestamp": 1564056219104
  },
  "CP-48-CR-0001995-2018": {
    "assignmentID": "cp0h2h09check4",
    "position": {
      "index": 0,
      "page": 0
    },
    "id": "CP-48-CR-0001995-2018",
    "filingDate": "6/20/2018 4:22:00 PM",
    "foundTimestamp": 1564056219145
  },
  "CP-45-CR-0001152-2018": {
    "assignmentID": "cp0h2h09check4",
    "position": {
      "index": 0,
      "page": 0
    },
    "id": "CP-45-CR-0001152-2018",
    "filingDate": "5/21/2018 8:38:00 AM",
    "foundTimestamp": 1564056219226
  },
  "CP-22-CR-0000902-2018": {
    "assignmentID": "cp0h2h09check4",
    "position": {
      "index": 0,
      "page": 0
    },
    "id": "CP-22-CR-0000902-2018",
    "filingDate": "2/14/2018 8:21:00 AM",
    "foundTimestamp": 1564056219266
  },
  "CP-67-CR-0000085-2018": {
    "assignmentID": "cp0h2h09check4",
    "position": {
      "index": 0,
      "page": 2
    },
    "id": "CP-67-CR-0000085-2018",
    "filingDate": "1/8/2018 10:58:00 AM",
    "foundTimestamp": 1564056232903
  },
  "CP-36-CR-0006469-2017": {
    "assignmentID": "cp0h2h09check4",
    "position": {
      "index": 0,
      "page": 2
    },
    "id": "CP-36-CR-0006469-2017",
    "filingDate": "12/19/2017 9:05:00 AM",
    "foundTimestamp": 1564056232943
  },
  "CP-06-CR-0005954-2017": {
    "assignmentID": "cp0h2h09check4",
    "position": {
      "index": 0,
      "page": 2
    },
    "id": "CP-06-CR-0005954-2017",
    "filingDate": "12/15/2017 4:22:00 PM",
    "foundTimestamp": 1564056232984
  },
  "CP-67-CR-0007612-2017": {
    "assignmentID": "cp0h2h09check4",
    "position": {
      "index": 0,
      "page": 2
    },
    "id": "CP-67-CR-0007612-2017",
    "filingDate": "12/1/2017 3:05:00 PM",
    "foundTimestamp": 1564056233025
  },
  "CP-67-CR-0005520-2017": {
    "assignmentID": "cp0h2h09check4",
    "position": {
      "index": 0,
      "page": 2
    },
    "id": "CP-67-CR-0005520-2017",
    "filingDate": "8/30/2017 1:46:00 PM",
    "foundTimestamp": 1564056233105
  },
  "CP-51-CR-0005542-2017": {
    "assignmentID": "cp0h2h09check4",
    "position": {
      "index": 0,
      "page": 2
    },
    "id": "CP-51-CR-0005542-2017",
    "filingDate": "6/29/2017 8:27:00 AM",
    "foundTimestamp": 1564056233192
  },
  "CP-36-CR-0002569-2017": {
    "assignmentID": "cp0h2h09check4",
    "position": {
      "index": 0,
      "page": 2
    },
    "id": "CP-36-CR-0002569-2017",
    "filingDate": "5/24/2017 4:42:00 PM",
    "foundTimestamp": 1564056233312
  },
  "CP-06-CR-0002542-2017": {
    "assignmentID": "cp0h2h09check4",
    "position": {
      "index": 0,
      "page": 2
    },
    "id": "CP-06-CR-0002542-2017",
    "filingDate": "5/22/2017 1:35:00 PM",
    "foundTimestamp": 1564056233353
  },
  "CP-25-CR-0001448-2017": {
    "assignmentID": "cp0h2h09check4",
    "position": {
      "index": 0,
      "page": 3
    },
    "id": "CP-25-CR-0001448-2017",
    "filingDate": "5/12/2017 9:22:00 AM",
    "foundTimestamp": 1564056246264
  },
  "CP-25-CR-0001301-2017": {
    "assignmentID": "cp0h2h09check4",
    "position": {
      "index": 0,
      "page": 3
    },
    "id": "CP-25-CR-0001301-2017",
    "filingDate": "5/1/2017 2:11:00 PM",
    "foundTimestamp": 1564056246350
  },
  "CP-67-CR-0002080-2017": {
    "assignmentID": "cp0h2h09check4",
    "position": {
      "index": 0,
      "page": 3
    },
    "id": "CP-67-CR-0002080-2017",
    "filingDate": "4/3/2017 3:04:00 PM",
    "foundTimestamp": 1564056246392
  },
  "CP-51-CR-0000392-2017": {
    "assignmentID": "cp0h2h09check4",
    "position": {
      "index": 0,
      "page": 3
    },
    "id": "CP-51-CR-0000392-2017",
    "filingDate": "1/17/2017 8:03:00 AM",
    "foundTimestamp": 1564056246471
  },
  "CP-51-CR-0000417-2017": {
    "assignmentID": "cp0h2h09check4",
    "position": {
      "index": 0,
      "page": 3
    },
    "id": "CP-51-CR-0000417-2017",
    "filingDate": "1/17/2017 8:03:00 AM",
    "foundTimestamp": 1564056246513
  },
  "CP-25-CR-0000054-2017": {
    "assignmentID": "cp0h2h09check4",
    "position": {
      "index": 0,
      "page": 3
    },
    "id": "CP-25-CR-0000054-2017",
    "filingDate": "1/6/2017 3:35:00 PM",
    "foundTimestamp": 1564056246594
  },
  "CP-19-CR-0000884-2016": {
    "assignmentID": "cp0h2h09check4",
    "position": {
      "index": 0,
      "page": 3
    },
    "id": "CP-19-CR-0000884-2016",
    "filingDate": "12/23/2016 11:19:00 AM",
    "foundTimestamp": 1564056246635
  },
  "CP-06-CR-0005600-2016": {
    "assignmentID": "cp0h2h09check4",
    "position": {
      "index": 0,
      "page": 3
    },
    "id": "CP-06-CR-0005600-2016",
    "filingDate": "12/14/2016 11:18:00 AM",
    "foundTimestamp": 1564056246675
  },
  "CP-67-CR-0006079-2016": {
    "assignmentID": "cp0h2h09check4",
    "position": {
      "index": 0,
      "page": 4
    },
    "id": "CP-67-CR-0006079-2016",
    "filingDate": "9/19/2016 2:41:00 PM",
    "foundTimestamp": 1564056259990
  },
  "CP-62-CR-0000240-2016": {
    "assignmentID": "cp0h2h09check4",
    "position": {
      "index": 0,
      "page": 4
    },
    "id": "CP-62-CR-0000240-2016",
    "filingDate": "7/21/2016 7:41:00 AM",
    "foundTimestamp": 1564056260031
  },
  "CP-36-CR-0002702-2016": {
    "assignmentID": "cp0h2h09check4",
    "position": {
      "index": 0,
      "page": 4
    },
    "id": "CP-36-CR-0002702-2016",
    "filingDate": "6/3/2016 11:36:00 AM",
    "foundTimestamp": 1564056260111
  },
  "CP-39-CR-0000596-2016": {
    "assignmentID": "cp0h2h09check4",
    "position": {
      "index": 0,
      "page": 4
    },
    "id": "CP-39-CR-0000596-2016",
    "filingDate": "2/8/2016 3:25:00 PM",
    "foundTimestamp": 1564056260113
  },
  "CP-09-CR-0006669-2015": {
    "assignmentID": "cp0h2h09check4",
    "position": {
      "index": 0,
      "page": 4
    },
    "id": "CP-09-CR-0006669-2015",
    "filingDate": "10/27/2015 12:00:00 PM",
    "foundTimestamp": 1564056260193
  },
  "CP-67-CR-0006085-2015": {
    "assignmentID": "cp0h2h09check4",
    "position": {
      "index": 0,
      "page": 4
    },
    "id": "CP-67-CR-0006085-2015",
    "filingDate": "9/23/2015 1:48:00 PM",
    "foundTimestamp": 1564056260234
  },
  "CP-06-CR-0004622-2015": {
    "assignmentID": "cp0h2h09check4",
    "position": {
      "index": 0,
      "page": 4
    },
    "id": "CP-06-CR-0004622-2015",
    "filingDate": "9/18/2015 3:38:00 PM",
    "foundTimestamp": 1564056260275
  },
  "CP-34-CR-0000136-2015": {
    "assignmentID": "cp0h2h09check4",
    "position": {
      "index": 0,
      "page": 4
    },
    "id": "CP-34-CR-0000136-2015",
    "filingDate": "7/20/2015 8:13:00 AM",
    "foundTimestamp": 1564056260316
  },
  "CP-11-CR-0001114-2015": {
    "assignmentID": "cp0h2h09check4",
    "position": {
      "index": 0,
      "page": 4
    },
    "id": "CP-11-CR-0001114-2015",
    "filingDate": "6/15/2015 12:05:00 PM",
    "foundTimestamp": 1564056260437
  },
  "CP-39-CR-0002219-2015": {
    "assignmentID": "cp0h2h09check4",
    "position": {
      "index": 0,
      "page": 5
    },
    "id": "CP-39-CR-0002219-2015",
    "filingDate": "5/22/2015 12:57:00 PM",
    "foundTimestamp": 1564056273327
  },
  "CP-39-CR-0000681-2015": {
    "assignmentID": "cp0h2h09check4",
    "position": {
      "index": 0,
      "page": 5
    },
    "id": "CP-39-CR-0000681-2015",
    "filingDate": "2/11/2015 10:56:00 AM",
    "foundTimestamp": 1564056273368
  },
  "CP-45-CR-0000171-2015": {
    "assignmentID": "cp0h2h09check4",
    "position": {
      "index": 0,
      "page": 5
    },
    "id": "CP-45-CR-0000171-2015",
    "filingDate": "1/22/2015 12:00:00 PM",
    "foundTimestamp": 1564056273410
  },
  "CP-49-CR-0001303-2014": {
    "assignmentID": "cp0h2h09check4",
    "position": {
      "index": 0,
      "page": 5
    },
    "id": "CP-49-CR-0001303-2014",
    "filingDate": "12/9/2014 3:04:00 PM",
    "foundTimestamp": 1564056273450
  },
  "CP-39-CR-0004782-2014": {
    "assignmentID": "cp0h2h09check4",
    "position": {
      "index": 0,
      "page": 5
    },
    "id": "CP-39-CR-0004782-2014",
    "filingDate": "10/30/2014 2:40:00 PM",
    "foundTimestamp": 1564056273491
  },
  "CP-36-CR-0004877-2014": {
    "assignmentID": "cp0h2h09check4",
    "position": {
      "index": 0,
      "page": 5
    },
    "id": "CP-36-CR-0004877-2014",
    "filingDate": "10/23/2014 1:12:00 PM",
    "foundTimestamp": 1564056273531
  },
  "CP-38-CR-0001554-2014": {
    "assignmentID": "cp0h2h09check4",
    "position": {
      "index": 0,
      "page": 5
    },
    "id": "CP-38-CR-0001554-2014",
    "filingDate": "9/19/2014 2:46:00 PM",
    "foundTimestamp": 1564056273576
  },
  "CP-22-CR-0004517-2014": {
    "assignmentID": "cp0h2h09check4",
    "position": {
      "index": 0,
      "page": 5
    },
    "id": "CP-22-CR-0004517-2014",
    "filingDate": "9/2/2014 8:00:00 AM",
    "foundTimestamp": 1564056273656
  },
  "CP-39-CR-0002569-2014": {
    "assignmentID": "cp0h2h09check4",
    "position": {
      "index": 0,
      "page": 6
    },
    "id": "CP-39-CR-0002569-2014",
    "filingDate": "6/16/2014 11:22:00 AM",
    "foundTimestamp": 1564056286232
  },
  "CP-36-CR-0002578-2014": {
    "assignmentID": "cp0h2h09check4",
    "position": {
      "index": 0,
      "page": 6
    },
    "id": "CP-36-CR-0002578-2014",
    "filingDate": "6/10/2014 3:51:00 PM",
    "foundTimestamp": 1564056286276
  },
  "CP-51-CR-0002565-2014": {
    "assignmentID": "cp0h2h09check4",
    "position": {
      "index": 0,
      "page": 6
    },
    "id": "CP-51-CR-0002565-2014",
    "filingDate": "3/7/2014 12:25:00 PM",
    "foundTimestamp": 1564056286278
  },
  "CP-46-CR-0001147-2014": {
    "assignmentID": "cp0h2h09check4",
    "position": {
      "index": 0,
      "page": 6
    },
    "id": "CP-46-CR-0001147-2014",
    "filingDate": "2/24/2014 9:22:00 AM",
    "foundTimestamp": 1564056286319
  },
  "CP-25-CR-0003586-2013": {
    "assignmentID": "cp0h2h09check4",
    "position": {
      "index": 0,
      "page": 6
    },
    "id": "CP-25-CR-0003586-2013",
    "filingDate": "12/6/2013 10:17:00 AM",
    "foundTimestamp": 1564056286359
  },
  "CP-07-CR-0002517-2013": {
    "assignmentID": "cp0h2h09check4",
    "position": {
      "index": 0,
      "page": 6
    },
    "id": "CP-07-CR-0002517-2013",
    "filingDate": "11/21/2013 8:44:00 AM",
    "foundTimestamp": 1564056286439
  },
  "CP-36-CR-0004573-2013": {
    "assignmentID": "cp0h2h09check4",
    "position": {
      "index": 0,
      "page": 6
    },
    "id": "CP-36-CR-0004573-2013",
    "filingDate": "10/4/2013 9:56:00 AM",
    "foundTimestamp": 1564056286520
  },
  "CP-67-CR-0005620-2013": {
    "assignmentID": "cp0h2h09check4",
    "position": {
      "index": 0,
      "page": 6
    },
    "id": "CP-67-CR-0005620-2013",
    "filingDate": "8/12/2013 3:26:00 PM",
    "foundTimestamp": 1564056286562
  },
  "CP-39-CR-0002678-2013": {
    "assignmentID": "cp0h2h09check4",
    "position": {
      "index": 0,
      "page": 6
    },
    "id": "CP-39-CR-0002678-2013",
    "filingDate": "6/19/2013 3:36:00 PM",
    "foundTimestamp": 1564056286642
  },
  "CP-28-CR-0000946-2013": {
    "assignmentID": "cp0h2h09check4",
    "position": {
      "index": 0,
      "page": 6
    },
    "id": "CP-28-CR-0000946-2013",
    "filingDate": "5/16/2013 9:37:00 AM",
    "foundTimestamp": 1564056286768
  },
  "CP-67-CR-0002428-2013": {
    "assignmentID": "cp0h2h09check4",
    "position": {
      "index": 0,
      "page": 7
    },
    "id": "CP-67-CR-0002428-2013",
    "filingDate": "4/8/2013 12:52:00 PM",
    "foundTimestamp": 1564056298161
  },
  "CP-38-CR-0000097-2013": {
    "assignmentID": "cp0h2h09check4",
    "position": {
      "index": 0,
      "page": 7
    },
    "id": "CP-38-CR-0000097-2013",
    "filingDate": "1/31/2013 3:49:00 PM",
    "foundTimestamp": 1564056298202
  },
  "CP-67-CR-0008979-2012": {
    "assignmentID": "cp0h2h09check4",
    "position": {
      "index": 0,
      "page": 7
    },
    "id": "CP-67-CR-0008979-2012",
    "filingDate": "12/19/2012 12:00:00 AM",
    "foundTimestamp": 1564056298288
  },
  "CP-06-CR-0005721-2012": {
    "assignmentID": "cp0h2h09check4",
    "position": {
      "index": 0,
      "page": 7
    },
    "id": "CP-06-CR-0005721-2012",
    "filingDate": "12/10/2012 1:03:00 PM",
    "foundTimestamp": 1564056298368
  },
  "CP-23-CR-0007522-2012": {
    "assignmentID": "cp0h2h09check4",
    "position": {
      "index": 0,
      "page": 7
    },
    "id": "CP-23-CR-0007522-2012",
    "filingDate": "11/14/2012 9:02:00 AM",
    "foundTimestamp": 1564056298408
  },
  "CP-46-CR-0008163-2012": {
    "assignmentID": "cp0h2h09check4",
    "position": {
      "index": 0,
      "page": 7
    },
    "id": "CP-46-CR-0008163-2012",
    "filingDate": "11/7/2012 7:49:00 AM",
    "foundTimestamp": 1564056298451
  },
  "CP-65-CR-0004045-2012": {
    "assignmentID": "cp0h2h09check4",
    "position": {
      "index": 0,
      "page": 7
    },
    "id": "CP-65-CR-0004045-2012",
    "filingDate": "10/23/2012 12:00:00 AM",
    "foundTimestamp": 1564056298491
  },
  "CP-38-CR-0001197-2012": {
    "assignmentID": "cp0h2h09check4",
    "position": {
      "index": 0,
      "page": 7
    },
    "id": "CP-38-CR-0001197-2012",
    "filingDate": "8/21/2012 11:31:00 AM",
    "foundTimestamp": 1564056298611
  },
  "CP-67-CR-0005252-2012": {
    "assignmentID": "cp0h2h09check4",
    "position": {
      "index": 0,
      "page": 7
    },
    "id": "CP-67-CR-0005252-2012",
    "filingDate": "7/17/2012 12:00:00 AM",
    "foundTimestamp": 1564056298695
  },
  "CP-67-CR-0003891-2012": {
    "assignmentID": "cp0h2h09check4",
    "position": {
      "index": 0,
      "page": 7
    },
    "id": "CP-67-CR-0003891-2012",
    "filingDate": "5/21/2012 12:00:00 AM",
    "foundTimestamp": 1564056298697
  },
  "CP-46-CR-0003260-2012": {
    "assignmentID": "cp0h2h09check4",
    "position": {
      "index": 0,
      "page": 8
    },
    "id": "CP-46-CR-0003260-2012",
    "filingDate": "4/30/2012 2:22:00 PM",
    "foundTimestamp": 1564056310927
  },
  "CP-48-CR-0001292-2012": {
    "assignmentID": "cp0h2h09check4",
    "position": {
      "index": 0,
      "page": 8
    },
    "id": "CP-48-CR-0001292-2012",
    "filingDate": "4/27/2012 12:00:00 AM",
    "foundTimestamp": 1564056311008
  },
  "CP-46-CR-0001241-2012": {
    "assignmentID": "cp0h2h09check4",
    "position": {
      "index": 0,
      "page": 8
    },
    "id": "CP-46-CR-0001241-2012",
    "filingDate": "2/17/2012 12:10:00 PM",
    "foundTimestamp": 1564056311049
  },
  "CP-45-CR-0002986-2011": {
    "assignmentID": "cp0h2h09check4",
    "position": {
      "index": 0,
      "page": 8
    },
    "id": "CP-45-CR-0002986-2011",
    "filingDate": "12/9/2011 12:26:00 PM",
    "foundTimestamp": 1564056311090
  },
  "CP-23-CR-0003416-2011": {
    "assignmentID": "cp0h2h09check4",
    "position": {
      "index": 0,
      "page": 8
    },
    "id": "CP-23-CR-0003416-2011",
    "filingDate": "6/20/2011 2:22:00 PM",
    "foundTimestamp": 1564056311175
  },
  "CP-51-CR-0005319-2011": {
    "assignmentID": "cp0h2h09check4",
    "position": {
      "index": 0,
      "page": 8
    },
    "id": "CP-51-CR-0005319-2011",
    "filingDate": "5/10/2011 10:23:00 AM",
    "foundTimestamp": 1564056311255
  },
  "CP-11-CR-0000767-2011": {
    "assignmentID": "cp0h2h09check4",
    "position": {
      "index": 0,
      "page": 8
    },
    "id": "CP-11-CR-0000767-2011",
    "filingDate": "4/27/2011 12:00:00 AM",
    "foundTimestamp": 1564056311296
  },
  "CP-48-CR-0001199-2011": {
    "assignmentID": "cp0h2h09check4",
    "position": {
      "index": 0,
      "page": 8
    },
    "id": "CP-48-CR-0001199-2011",
    "filingDate": "4/19/2011 12:00:00 AM",
    "foundTimestamp": 1564056311377
  },
  "CP-36-CR-0001413-2011": {
    "assignmentID": "cp0h2h09check4",
    "position": {
      "index": 0,
      "page": 8
    },
    "id": "CP-36-CR-0001413-2011",
    "filingDate": "4/6/2011 12:00:00 AM",
    "foundTimestamp": 1564056311419
  },
  "CP-46-CR-0002170-2011": {
    "assignmentID": "cp0h2h09check4",
    "position": {
      "index": 0,
      "page": 9
    },
    "id": "CP-46-CR-0002170-2011",
    "filingDate": "3/28/2011 3:06:00 PM",
    "foundTimestamp": 1564056325524
  },
  "CP-15-CR-0000750-2011": {
    "assignmentID": "cp0h2h09check4",
    "position": {
      "index": 0,
      "page": 9
    },
    "id": "CP-15-CR-0000750-2011",
    "filingDate": "3/2/2011 8:25:00 AM",
    "foundTimestamp": 1564056325527
  },
  "CP-67-CR-0005921-2010": {
    "assignmentID": "cp0h2h09check4",
    "position": {
      "index": 0,
      "page": 9
    },
    "id": "CP-67-CR-0005921-2010",
    "filingDate": "10/8/2010 12:00:00 AM",
    "foundTimestamp": 1564056325607
  },
  "CP-06-CR-0003355-2010": {
    "assignmentID": "cp0h2h09check4",
    "position": {
      "index": 0,
      "page": 9
    },
    "id": "CP-06-CR-0003355-2010",
    "filingDate": "8/30/2010 3:58:00 PM",
    "foundTimestamp": 1564056325647
  },
  "CP-06-CR-0003359-2010": {
    "assignmentID": "cp0h2h09check4",
    "position": {
      "index": 0,
      "page": 9
    },
    "id": "CP-06-CR-0003359-2010",
    "filingDate": "8/30/2010 3:58:00 PM",
    "foundTimestamp": 1564056325688
  },
  "CP-06-CR-0003058-2010": {
    "assignmentID": "cp0h2h09check4",
    "position": {
      "index": 0,
      "page": 9
    },
    "id": "CP-06-CR-0003058-2010",
    "filingDate": "8/9/2010 1:22:00 PM",
    "foundTimestamp": 1564056325729
  },
  "CP-07-CR-0000950-2010": {
    "assignmentID": "cp0h2h09check4",
    "position": {
      "index": 0,
      "page": 9
    },
    "id": "CP-07-CR-0000950-2010",
    "filingDate": "5/13/2010 10:06:00 AM",
    "foundTimestamp": 1564056325851
  },
  "CP-07-CR-0000821-2010": {
    "assignmentID": "cp0h2h09check4",
    "position": {
      "index": 0,
      "page": 9
    },
    "id": "CP-07-CR-0000821-2010",
    "filingDate": "4/28/2010 2:13:00 PM",
    "foundTimestamp": 1564056325976
  },
  "CP-51-CR-0004594-2010": {
    "assignmentID": "cp0h2h09check4",
    "position": {
      "index": 0,
      "page": 9
    },
    "id": "CP-51-CR-0004594-2010",
    "filingDate": "4/15/2010 9:22:00 AM",
    "foundTimestamp": 1564056326018
  },
  "CP-28-CR-0000634-2010": {
    "assignmentID": "cp0h2h09check4",
    "position": {
      "index": 0,
      "page": 10
    },
    "id": "CP-28-CR-0000634-2010",
    "filingDate": "3/29/2010 12:00:00 AM",
    "foundTimestamp": 1564056340064
  },
  "CP-39-CR-0000530-2010": {
    "assignmentID": "cp0h2h09check4",
    "position": {
      "index": 0,
      "page": 10
    },
    "id": "CP-39-CR-0000530-2010",
    "filingDate": "2/5/2010 9:38:00 AM",
    "foundTimestamp": 1564056340105
  },
  "CP-46-CR-0000068-2010": {
    "assignmentID": "cp0h2h09check4",
    "position": {
      "index": 0,
      "page": 10
    },
    "id": "CP-46-CR-0000068-2010",
    "filingDate": "1/8/2010 11:00:00 AM",
    "foundTimestamp": 1564056340146
  },
  "CP-23-CR-0007052-2009": {
    "assignmentID": "cp0h2h09check4",
    "position": {
      "index": 0,
      "page": 10
    },
    "id": "CP-23-CR-0007052-2009",
    "filingDate": "11/23/2009 11:17:00 AM",
    "foundTimestamp": 1564056340188
  },
  "CP-07-CR-0002407-2009": {
    "assignmentID": "cp0h2h09check4",
    "position": {
      "index": 0,
      "page": 10
    },
    "id": "CP-07-CR-0002407-2009",
    "filingDate": "10/29/2009 9:43:00 AM",
    "foundTimestamp": 1564056340268
  },
  "CP-07-CR-0002397-2009": {
    "assignmentID": "cp0h2h09check4",
    "position": {
      "index": 0,
      "page": 10
    },
    "id": "CP-07-CR-0002397-2009",
    "filingDate": "10/22/2009 2:17:00 PM",
    "foundTimestamp": 1564056340345
  },
  "CP-48-CR-0003403-2009": {
    "assignmentID": "cp0h2h09check4",
    "position": {
      "index": 0,
      "page": 10
    },
    "id": "CP-48-CR-0003403-2009",
    "filingDate": "10/21/2009 1:54:00 PM",
    "foundTimestamp": 1564056340426
  },
  "CP-39-CR-0004058-2009": {
    "assignmentID": "cp0h2h09check4",
    "position": {
      "index": 0,
      "page": 11
    },
    "id": "CP-39-CR-0004058-2009",
    "filingDate": "10/2/2009 10:45:00 AM",
    "foundTimestamp": 1564056354642
  },
  "CP-51-CR-0012708-2009": {
    "assignmentID": "cp0h2h09check4",
    "position": {
      "index": 0,
      "page": 11
    },
    "id": "CP-51-CR-0012708-2009",
    "filingDate": "10/2/2009 9:38:00 AM",
    "foundTimestamp": 1564056354684
  },
  "CP-15-CR-0003879-2009": {
    "assignmentID": "cp0h2h09check4",
    "position": {
      "index": 0,
      "page": 11
    },
    "id": "CP-15-CR-0003879-2009",
    "filingDate": "9/18/2009 4:58:00 PM",
    "foundTimestamp": 1564056354763
  },
  "CP-36-CR-0003270-2009": {
    "assignmentID": "cp0h2h09check4",
    "position": {
      "index": 0,
      "page": 11
    },
    "id": "CP-36-CR-0003270-2009",
    "filingDate": "7/27/2009 12:00:00 AM",
    "foundTimestamp": 1564056354804
  },
  "CP-22-CR-0002486-2009": {
    "assignmentID": "cp0h2h09check4",
    "position": {
      "index": 0,
      "page": 11
    },
    "id": "CP-22-CR-0002486-2009",
    "filingDate": "6/5/2009 8:39:00 AM",
    "foundTimestamp": 1564056354846
  },
  "CP-67-CR-0003341-2009": {
    "assignmentID": "cp0h2h09check4",
    "position": {
      "index": 0,
      "page": 11
    },
    "id": "CP-67-CR-0003341-2009",
    "filingDate": "6/5/2009 12:00:00 AM",
    "foundTimestamp": 1564056354930
  },
  "CP-06-CR-0002308-2009": {
    "assignmentID": "cp0h2h09check4",
    "position": {
      "index": 0,
      "page": 11
    },
    "id": "CP-06-CR-0002308-2009",
    "filingDate": "5/26/2009 3:30:00 PM",
    "foundTimestamp": 1564056354967
  },
  "CP-36-CR-0002127-2009": {
    "assignmentID": "cp0h2h09check4",
    "position": {
      "index": 0,
      "page": 11
    },
    "id": "CP-36-CR-0002127-2009",
    "filingDate": "5/14/2009 12:00:00 AM",
    "foundTimestamp": 1564056355012
  },
  "CP-51-CR-0005894-2009": {
    "assignmentID": "cp0h2h09check4",
    "position": {
      "index": 0,
      "page": 11
    },
    "id": "CP-51-CR-0005894-2009",
    "filingDate": "5/5/2009 9:29:00 AM",
    "foundTimestamp": 1564056355052
  },
  "CP-06-CR-0001381-2009": {
    "assignmentID": "cp0h2h09check4",
    "position": {
      "index": 0,
      "page": 11
    },
    "id": "CP-06-CR-0001381-2009",
    "filingDate": "3/30/2009 3:18:00 PM",
    "foundTimestamp": 1564056355133
  },
  "CP-11-CR-0000469-2009": {
    "assignmentID": "cp0h2h09check4",
    "position": {
      "index": 0,
      "page": 12
    },
    "id": "CP-11-CR-0000469-2009",
    "filingDate": "3/18/2009 12:00:00 AM",
    "foundTimestamp": 1564056370572
  },
  "CP-06-CR-0000799-2009": {
    "assignmentID": "cp0h2h09check4",
    "position": {
      "index": 0,
      "page": 12
    },
    "id": "CP-06-CR-0000799-2009",
    "filingDate": "2/23/2009 4:31:00 PM",
    "foundTimestamp": 1564056370613
  },
  "CP-07-CR-0000369-2009": {
    "assignmentID": "cp0h2h09check4",
    "position": {
      "index": 0,
      "page": 12
    },
    "id": "CP-07-CR-0000369-2009",
    "filingDate": "2/13/2009 10:00:00 AM",
    "foundTimestamp": 1564056370774
  },
  "CP-22-CR-0000672-2009": {
    "assignmentID": "cp0h2h09check4",
    "position": {
      "index": 0,
      "page": 12
    },
    "id": "CP-22-CR-0000672-2009",
    "filingDate": "2/13/2009 9:53:00 AM",
    "foundTimestamp": 1564056370856
  },
  "CP-65-CR-0000207-2019": {
    "assignmentID": "cp0h2h09check4",
    "position": {
      "index": 8,
      "page": 0
    },
    "id": "CP-65-CR-0000207-2019",
    "filingDate": "1/17/2019 12:42:00 PM",
    "foundTimestamp": 1564056520857
  },
  "CP-45-CR-0001514-2019": {
    "assignmentID": "cp0h2h09check4",
    "position": {
      "index": 13,
      "page": 0
    },
    "id": "CP-45-CR-0001514-2019",
    "filingDate": "6/25/2019 11:11:00 AM",
    "foundTimestamp": 1564056614144
  },
  "CP-45-CR-0001528-2019": {
    "assignmentID": "cp0h2h09check4",
    "position": {
      "index": 13,
      "page": 0
    },
    "id": "CP-45-CR-0001528-2019",
    "filingDate": "6/25/2019 11:11:00 AM",
    "foundTimestamp": 1564056614153
  },
  "CP-66-CR-0000185-2019": {
    "assignmentID": "cp0h2h09check4",
    "position": {
      "index": 13,
      "page": 0
    },
    "id": "CP-66-CR-0000185-2019",
    "filingDate": "6/13/2019 3:16:00 PM",
    "foundTimestamp": 1564056614155
  },
  "CP-02-CR-0005848-2019": {
    "assignmentID": "cp0h2h09check4",
    "position": {
      "index": 13,
      "page": 0
    },
    "id": "CP-02-CR-0005848-2019",
    "filingDate": "6/4/2019 1:47:00 PM",
    "foundTimestamp": 1564056614159
  },
  "CP-02-CR-0005849-2019": {
    "assignmentID": "cp0h2h09check4",
    "position": {
      "index": 13,
      "page": 0
    },
    "id": "CP-02-CR-0005849-2019",
    "filingDate": "6/4/2019 1:47:00 PM",
    "foundTimestamp": 1564056614161
  },
  "CP-67-CR-0003021-2019": {
    "assignmentID": "cp0h2h09check4",
    "position": {
      "index": 13,
      "page": 0
    },
    "id": "CP-67-CR-0003021-2019",
    "filingDate": "5/9/2019 1:24:00 PM",
    "foundTimestamp": 1564056614163
  },
  "CP-54-CR-0000747-2019": {
    "assignmentID": "cp0h2h09check4",
    "position": {
      "index": 13,
      "page": 2
    },
    "id": "CP-54-CR-0000747-2019",
    "filingDate": "5/2/2019 12:19:00 PM",
    "foundTimestamp": 1564056640836
  },
  "CP-67-CR-0002772-2019": {
    "assignmentID": "cp0h2h09check4",
    "position": {
      "index": 13,
      "page": 2
    },
    "id": "CP-67-CR-0002772-2019",
    "filingDate": "4/30/2019 1:49:00 PM",
    "foundTimestamp": 1564056640881
  },
  "CP-67-CR-0002718-2019": {
    "assignmentID": "cp0h2h09check4",
    "position": {
      "index": 13,
      "page": 2
    },
    "id": "CP-67-CR-0002718-2019",
    "filingDate": "4/26/2019 4:03:00 PM",
    "foundTimestamp": 1564056640963
  },
  "CP-46-CR-0002563-2019": {
    "assignmentID": "cp0h2h09check4",
    "position": {
      "index": 13,
      "page": 2
    },
    "id": "CP-46-CR-0002563-2019",
    "filingDate": "4/26/2019 10:56:00 AM",
    "foundTimestamp": 1564056641043
  },
  "CP-51-CR-0002968-2019": {
    "assignmentID": "cp0h2h09check4",
    "position": {
      "index": 13,
      "page": 2
    },
    "id": "CP-51-CR-0002968-2019",
    "filingDate": "4/26/2019 9:15:00 AM",
    "foundTimestamp": 1564056641084
  },
  "CP-06-CR-0001823-2019": {
    "assignmentID": "cp0h2h09check4",
    "position": {
      "index": 13,
      "page": 2
    },
    "id": "CP-06-CR-0001823-2019",
    "filingDate": "4/24/2019 9:59:00 AM",
    "foundTimestamp": 1564056641250
  },
  "CP-19-CR-0000456-2019": {
    "assignmentID": "cp0h2h09check4",
    "position": {
      "index": 13,
      "page": 2
    },
    "id": "CP-19-CR-0000456-2019",
    "filingDate": "4/22/2019 2:49:00 PM",
    "foundTimestamp": 1564056641291
  },
  "CP-22-CR-0001726-2019": {
    "assignmentID": "cp0h2h09check4",
    "position": {
      "index": 13,
      "page": 2
    },
    "id": "CP-22-CR-0001726-2019",
    "filingDate": "4/1/2019 4:01:00 PM",
    "foundTimestamp": 1564056641413
  },
  "CP-61-CR-0000250-2019": {
    "assignmentID": "cp0h2h09check4",
    "position": {
      "index": 13,
      "page": 2
    },
    "id": "CP-61-CR-0000250-2019",
    "filingDate": "3/21/2019 2:25:00 PM",
    "foundTimestamp": 1564056641454
  },
  "CP-67-CR-0001823-2019": {
    "assignmentID": "cp0h2h09check4",
    "position": {
      "index": 13,
      "page": 3
    },
    "id": "CP-67-CR-0001823-2019",
    "filingDate": "3/19/2019 4:25:00 PM",
    "foundTimestamp": 1564057151697
  },
  "CP-09-CR-0001467-2019": {
    "assignmentID": "cp0h2h09check4",
    "position": {
      "index": 13,
      "page": 3
    },
    "id": "CP-09-CR-0001467-2019",
    "filingDate": "3/18/2019 11:33:00 AM",
    "foundTimestamp": 1564057151765
  },
  "CP-39-CR-0000999-2019": {
    "assignmentID": "cp0h2h09check4",
    "position": {
      "index": 13,
      "page": 3
    },
    "id": "CP-39-CR-0000999-2019",
    "filingDate": "3/7/2019 11:26:00 AM",
    "foundTimestamp": 1564057151810
  },
  "CP-25-CR-0000510-2019": {
    "assignmentID": "cp0h2h09check4",
    "position": {
      "index": 13,
      "page": 3
    },
    "id": "CP-25-CR-0000510-2019",
    "filingDate": "2/19/2019 4:14:00 PM",
    "foundTimestamp": 1564057151891
  },
  "CP-67-CR-0001056-2019": {
    "assignmentID": "cp0h2h09check4",
    "position": {
      "index": 13,
      "page": 3
    },
    "id": "CP-67-CR-0001056-2019",
    "filingDate": "2/14/2019 4:28:00 PM",
    "foundTimestamp": 1564057151932
  },
  "CP-67-CR-0001040-2019": {
    "assignmentID": "cp0h2h09check4",
    "position": {
      "index": 13,
      "page": 3
    },
    "id": "CP-67-CR-0001040-2019",
    "filingDate": "2/14/2019 4:24:00 PM",
    "foundTimestamp": 1564057151973
  },
  "CP-23-CR-0000600-2019": {
    "assignmentID": "cp0h2h09check4",
    "position": {
      "index": 13,
      "page": 3
    },
    "id": "CP-23-CR-0000600-2019",
    "filingDate": "2/1/2019 3:10:00 PM",
    "foundTimestamp": 1564057152053
  },
  "CP-23-CR-0000592-2019": {
    "assignmentID": "cp0h2h09check4",
    "position": {
      "index": 13,
      "page": 3
    },
    "id": "CP-23-CR-0000592-2019",
    "filingDate": "2/1/2019 1:02:00 PM",
    "foundTimestamp": 1564057152095
  },
  "CP-65-CR-0000330-2019": {
    "assignmentID": "cp0h2h09check4",
    "position": {
      "index": 13,
      "page": 3
    },
    "id": "CP-65-CR-0000330-2019",
    "filingDate": "1/24/2019 11:46:00 AM",
    "foundTimestamp": 1564057152220
  },
  "CP-23-CR-0000416-2019": {
    "assignmentID": "cp0h2h09check4",
    "position": {
      "index": 13,
      "page": 4
    },
    "id": "CP-23-CR-0000416-2019",
    "filingDate": "1/24/2019 11:45:00 AM",
    "foundTimestamp": 1564057174858
  },
  "CP-19-CR-0000075-2019": {
    "assignmentID": "cp0h2h09check4",
    "position": {
      "index": 13,
      "page": 4
    },
    "id": "CP-19-CR-0000075-2019",
    "filingDate": "1/17/2019 10:13:00 AM",
    "foundTimestamp": 1564057174938
  },
  "CP-02-CR-0015553-2018": {
    "assignmentID": "cp0h2h09check4",
    "position": {
      "index": 13,
      "page": 4
    },
    "id": "CP-02-CR-0015553-2018",
    "filingDate": "12/28/2018 3:58:00 PM",
    "foundTimestamp": 1564057174979
  },
  "CP-65-CR-0004974-2018": {
    "assignmentID": "cp0h2h09check4",
    "position": {
      "index": 13,
      "page": 4
    },
    "id": "CP-65-CR-0004974-2018",
    "filingDate": "12/7/2018 1:45:00 PM",
    "foundTimestamp": 1564057175024
  },
  "CP-67-CR-0007178-2018": {
    "assignmentID": "cp0h2h09check4",
    "position": {
      "index": 13,
      "page": 4
    },
    "id": "CP-67-CR-0007178-2018",
    "filingDate": "12/6/2018 12:07:00 PM",
    "foundTimestamp": 1564057175065
  },
  "CP-40-CR-0004138-2018": {
    "assignmentID": "cp0h2h09check4",
    "position": {
      "index": 13,
      "page": 4
    },
    "id": "CP-40-CR-0004138-2018",
    "filingDate": "12/4/2018 9:29:00 AM",
    "foundTimestamp": 1564057175106
  },
  "CP-36-CR-0005991-2018": {
    "assignmentID": "cp0h2h09check4",
    "position": {
      "index": 13,
      "page": 4
    },
    "id": "CP-36-CR-0005991-2018",
    "filingDate": "10/19/2018 8:57:00 AM",
    "foundTimestamp": 1564057175187
  },
  "CP-28-CR-0001870-2018": {
    "assignmentID": "cp0h2h09check4",
    "position": {
      "index": 13,
      "page": 4
    },
    "id": "CP-28-CR-0001870-2018",
    "filingDate": "10/12/2018 9:29:00 AM",
    "foundTimestamp": 1564057175267
  },
  "CP-36-CR-0005805-2018": {
    "assignmentID": "cp0h2h09check4",
    "position": {
      "index": 13,
      "page": 4
    },
    "id": "CP-36-CR-0005805-2018",
    "filingDate": "10/11/2018 10:09:00 AM",
    "foundTimestamp": 1564057175308
  },
  "CP-22-CR-0005402-2018": {
    "assignmentID": "cp0h2h09check4",
    "position": {
      "index": 13,
      "page": 4
    },
    "id": "CP-22-CR-0005402-2018",
    "filingDate": "10/10/2018 2:36:00 PM",
    "foundTimestamp": 1564057175387
  },
  "CP-52-CR-0000437-2018": {
    "assignmentID": "cp0h2h09check4",
    "position": {
      "index": 13,
      "page": 5
    },
    "id": "CP-52-CR-0000437-2018",
    "filingDate": "10/9/2018 11:37:00 AM",
    "foundTimestamp": 1564057194870
  },
  "CP-10-CR-0001742-2018": {
    "assignmentID": "cp0h2h09check4",
    "position": {
      "index": 13,
      "page": 5
    },
    "id": "CP-10-CR-0001742-2018",
    "filingDate": "10/4/2018 9:26:00 AM",
    "foundTimestamp": 1564057194910
  },
  "CP-67-CR-0005843-2018": {
    "assignmentID": "cp0h2h09check4",
    "position": {
      "index": 13,
      "page": 5
    },
    "id": "CP-67-CR-0005843-2018",
    "filingDate": "10/2/2018 2:32:00 PM",
    "foundTimestamp": 1564057194989
  },
  "CP-54-CR-0001444-2018": {
    "assignmentID": "cp0h2h09check4",
    "position": {
      "index": 13,
      "page": 5
    },
    "id": "CP-54-CR-0001444-2018",
    "filingDate": "8/1/2018 2:02:00 PM",
    "foundTimestamp": 1564057195030
  },
  "CP-48-CR-0002305-2018": {
    "assignmentID": "cp0h2h09check4",
    "position": {
      "index": 13,
      "page": 5
    },
    "id": "CP-48-CR-0002305-2018",
    "filingDate": "7/23/2018 2:29:00 PM",
    "foundTimestamp": 1564057195032
  },
  "CP-51-CR-0005033-2018": {
    "assignmentID": "cp0h2h09check4",
    "position": {
      "index": 13,
      "page": 5
    },
    "id": "CP-51-CR-0005033-2018",
    "filingDate": "7/13/2018 8:10:00 AM",
    "foundTimestamp": 1564057195112
  },
  "CP-51-CR-0005034-2018": {
    "assignmentID": "cp0h2h09check4",
    "position": {
      "index": 13,
      "page": 5
    },
    "id": "CP-51-CR-0005034-2018",
    "filingDate": "7/13/2018 8:10:00 AM",
    "foundTimestamp": 1564057195192
  },
  "CP-02-CR-0007543-2018": {
    "assignmentID": "cp0h2h09check4",
    "position": {
      "index": 13,
      "page": 5
    },
    "id": "CP-02-CR-0007543-2018",
    "filingDate": "6/21/2018 1:03:00 PM",
    "foundTimestamp": 1564057195237
  },
  "CP-65-CR-0002045-2018": {
    "assignmentID": "cp0h2h09check4",
    "position": {
      "index": 13,
      "page": 6
    },
    "id": "CP-65-CR-0002045-2018",
    "filingDate": "5/17/2018 1:22:00 PM",
    "foundTimestamp": 1564057208587
  },
  "CP-09-CR-0002890-2018": {
    "assignmentID": "cp0h2h09check4",
    "position": {
      "index": 13,
      "page": 6
    },
    "id": "CP-09-CR-0002890-2018",
    "filingDate": "5/14/2018 1:17:00 PM",
    "foundTimestamp": 1564057208628
  },
  "CP-54-CR-0000694-2018": {
    "assignmentID": "cp0h2h09check4",
    "position": {
      "index": 13,
      "page": 6
    },
    "id": "CP-54-CR-0000694-2018",
    "filingDate": "4/30/2018 10:16:00 AM",
    "foundTimestamp": 1564057208631
  },
  "CP-19-CR-0000355-2018": {
    "assignmentID": "cp0h2h09check4",
    "position": {
      "index": 13,
      "page": 6
    },
    "id": "CP-19-CR-0000355-2018",
    "filingDate": "4/16/2018 12:32:00 PM",
    "foundTimestamp": 1564057208633
  },
  "CP-66-CR-0000100-2018": {
    "assignmentID": "cp0h2h09check4",
    "position": {
      "index": 13,
      "page": 6
    },
    "id": "CP-66-CR-0000100-2018",
    "filingDate": "3/22/2018 1:43:00 PM",
    "foundTimestamp": 1564057208637
  },
  "CP-54-CR-0000492-2018": {
    "assignmentID": "cp0h2h09check4",
    "position": {
      "index": 13,
      "page": 6
    },
    "id": "CP-54-CR-0000492-2018",
    "filingDate": "3/22/2018 1:42:00 PM",
    "foundTimestamp": 1564057208639
  },
  "CP-45-CR-0000522-2018": {
    "assignmentID": "cp0h2h09check4",
    "position": {
      "index": 13,
      "page": 6
    },
    "id": "CP-45-CR-0000522-2018",
    "filingDate": "3/13/2018 9:39:00 AM",
    "foundTimestamp": 1564057208640
  },
  "CP-02-CR-0002949-2018": {
    "assignmentID": "cp0h2h09check4",
    "position": {
      "index": 13,
      "page": 6
    },
    "id": "CP-02-CR-0002949-2018",
    "filingDate": "3/9/2018 8:46:00 AM",
    "foundTimestamp": 1564057208642
  },
  "CP-02-CR-0002950-2018": {
    "assignmentID": "cp0h2h09check4",
    "position": {
      "index": 13,
      "page": 6
    },
    "id": "CP-02-CR-0002950-2018",
    "filingDate": "3/9/2018 8:46:00 AM",
    "foundTimestamp": 1564057208644
  },
  "CP-46-CR-0001298-2018": {
    "assignmentID": "cp0h2h09check4",
    "position": {
      "index": 13,
      "page": 6
    },
    "id": "CP-46-CR-0001298-2018",
    "filingDate": "2/26/2018 3:36:00 PM",
    "foundTimestamp": 1564057208646
  },
  "CP-02-CR-0002081-2018": {
    "assignmentID": "cp0h2h09check4",
    "position": {
      "index": 13,
      "page": 7
    },
    "id": "CP-02-CR-0002081-2018",
    "filingDate": "2/20/2018 1:12:00 PM",
    "foundTimestamp": 1564057222270
  },
  "CP-63-CR-0000389-2018": {
    "assignmentID": "cp0h2h09check4",
    "position": {
      "index": 13,
      "page": 7
    },
    "id": "CP-63-CR-0000389-2018",
    "filingDate": "2/20/2018 12:44:00 PM",
    "foundTimestamp": 1564057222287
  },
  "CP-45-CR-0000320-2018": {
    "assignmentID": "cp0h2h09check4",
    "position": {
      "index": 13,
      "page": 7
    },
    "id": "CP-45-CR-0000320-2018",
    "filingDate": "2/14/2018 10:53:00 AM",
    "foundTimestamp": 1564057222290
  },
  "CP-51-CR-0000724-2018": {
    "assignmentID": "cp0h2h09check4",
    "position": {
      "index": 13,
      "page": 7
    },
    "id": "CP-51-CR-0000724-2018",
    "filingDate": "1/26/2018 8:24:00 AM",
    "foundTimestamp": 1564057222294
  },
  "CP-36-CR-0000480-2018": {
    "assignmentID": "cp0h2h09check4",
    "position": {
      "index": 13,
      "page": 7
    },
    "id": "CP-36-CR-0000480-2018",
    "filingDate": "1/19/2018 3:49:00 PM",
    "foundTimestamp": 1564057222296
  },
  "CP-65-CR-0000148-2018": {
    "assignmentID": "cp0h2h09check4",
    "position": {
      "index": 13,
      "page": 7
    },
    "id": "CP-65-CR-0000148-2018",
    "filingDate": "1/10/2018 2:06:00 PM",
    "foundTimestamp": 1564057222301
  },
  "CP-46-CR-0000079-2018": {
    "assignmentID": "cp0h2h09check4",
    "position": {
      "index": 13,
      "page": 7
    },
    "id": "CP-46-CR-0000079-2018",
    "filingDate": "1/5/2018 2:20:00 PM",
    "foundTimestamp": 1564057222312
  },
  "CP-46-CR-0008428-2017": {
    "assignmentID": "cp0h2h09check4",
    "position": {
      "index": 13,
      "page": 7
    },
    "id": "CP-46-CR-0008428-2017",
    "filingDate": "12/19/2017 2:14:00 PM",
    "foundTimestamp": 1564057222314
  },
  "CP-25-CR-0004038-2017": {
    "assignmentID": "cp0h2h09check4",
    "position": {
      "index": 13,
      "page": 7
    },
    "id": "CP-25-CR-0004038-2017",
    "filingDate": "12/18/2017 12:15:00 PM",
    "foundTimestamp": 1564057222316
  },
  "CP-02-CR-0015372-2017": {
    "assignmentID": "cp0h2h09check4",
    "position": {
      "index": 13,
      "page": 7
    },
    "id": "CP-02-CR-0015372-2017",
    "filingDate": "12/15/2017 12:13:00 PM",
    "foundTimestamp": 1564057222320
  },
  "CP-65-CR-0005105-2017": {
    "assignmentID": "cp0h2h09check4",
    "position": {
      "index": 13,
      "page": 8
    },
    "id": "CP-65-CR-0005105-2017",
    "filingDate": "11/20/2017 11:28:00 AM",
    "foundTimestamp": 1564057243511
  },
  "CP-62-CR-0000415-2017": {
    "assignmentID": "cp0h2h09check4",
    "position": {
      "index": 13,
      "page": 8
    },
    "id": "CP-62-CR-0000415-2017",
    "filingDate": "11/2/2017 8:32:00 AM",
    "foundTimestamp": 1564057243591
  },
  "CP-67-CR-0006181-2017": {
    "assignmentID": "cp0h2h09check4",
    "position": {
      "index": 13,
      "page": 8
    },
    "id": "CP-67-CR-0006181-2017",
    "filingDate": "9/28/2017 2:39:00 PM",
    "foundTimestamp": 1564057243673
  },
  "CP-23-CR-0005508-2017": {
    "assignmentID": "cp0h2h09check4",
    "position": {
      "index": 13,
      "page": 8
    },
    "id": "CP-23-CR-0005508-2017",
    "filingDate": "9/15/2017 1:17:00 PM",
    "foundTimestamp": 1564057243714
  },
  "CP-36-CR-0004587-2017": {
    "assignmentID": "cp0h2h09check4",
    "position": {
      "index": 13,
      "page": 8
    },
    "id": "CP-36-CR-0004587-2017",
    "filingDate": "9/8/2017 1:47:00 PM",
    "foundTimestamp": 1564057243759
  },
  "CP-31-CR-0000388-2017": {
    "assignmentID": "cp0h2h09check4",
    "position": {
      "index": 13,
      "page": 8
    },
    "id": "CP-31-CR-0000388-2017",
    "filingDate": "8/2/2017 3:48:00 PM",
    "foundTimestamp": 1564057243840
  },
  "CP-36-CR-0003764-2017": {
    "assignmentID": "cp0h2h09check4",
    "position": {
      "index": 13,
      "page": 8
    },
    "id": "CP-36-CR-0003764-2017",
    "filingDate": "7/28/2017 10:08:00 AM",
    "foundTimestamp": 1564057243920
  },
  "CP-02-CR-0007369-2017": {
    "assignmentID": "cp0h2h09check4",
    "position": {
      "index": 13,
      "page": 9
    },
    "id": "CP-02-CR-0007369-2017",
    "filingDate": "6/21/2017 10:43:00 AM",
    "foundTimestamp": 1564057266052
  },
  "CP-36-CR-0002510-2017": {
    "assignmentID": "cp0h2h09check4",
    "position": {
      "index": 13,
      "page": 9
    },
    "id": "CP-36-CR-0002510-2017",
    "filingDate": "5/18/2017 2:26:00 PM",
    "foundTimestamp": 1564057266092
  },
  "CP-11-CR-0000767-2017": {
    "assignmentID": "cp0h2h09check4",
    "position": {
      "index": 13,
      "page": 9
    },
    "id": "CP-11-CR-0000767-2017",
    "filingDate": "5/15/2017 2:26:00 PM",
    "foundTimestamp": 1564057266133
  },
  "CP-67-CR-0002809-2017": {
    "assignmentID": "cp0h2h09check4",
    "position": {
      "index": 13,
      "page": 9
    },
    "id": "CP-67-CR-0002809-2017",
    "filingDate": "5/2/2017 12:18:00 PM",
    "foundTimestamp": 1564057266214
  },
  "CP-64-CR-0000104-2017": {
    "assignmentID": "cp0h2h09check4",
    "position": {
      "index": 13,
      "page": 9
    },
    "id": "CP-64-CR-0000104-2017",
    "filingDate": "4/24/2017 8:52:00 AM",
    "foundTimestamp": 1564057266260
  },
  "CP-41-CR-0000563-2017": {
    "assignmentID": "cp0h2h09check4",
    "position": {
      "index": 13,
      "page": 9
    },
    "id": "CP-41-CR-0000563-2017",
    "filingDate": "3/30/2017 3:03:00 PM",
    "foundTimestamp": 1564057266341
  },
  "CP-39-CR-0001084-2017": {
    "assignmentID": "cp0h2h09check4",
    "position": {
      "index": 13,
      "page": 9
    },
    "id": "CP-39-CR-0001084-2017",
    "filingDate": "3/15/2017 1:43:00 PM",
    "foundTimestamp": 1564057266420
  },
  "CP-15-CR-0000890-2017": {
    "assignmentID": "cp0h2h09check4",
    "position": {
      "index": 13,
      "page": 9
    },
    "id": "CP-15-CR-0000890-2017",
    "filingDate": "3/10/2017 8:48:00 AM",
    "foundTimestamp": 1564057266460
  },
  "CP-25-CR-0000603-2017": {
    "assignmentID": "cp0h2h09check4",
    "position": {
      "index": 13,
      "page": 9
    },
    "id": "CP-25-CR-0000603-2017",
    "filingDate": "2/28/2017 3:36:00 PM",
    "foundTimestamp": 1564057266463
  },
  "CP-09-CR-0001419-2017": {
    "assignmentID": "cp0h2h09check4",
    "position": {
      "index": 13,
      "page": 10
    },
    "id": "CP-09-CR-0001419-2017",
    "filingDate": "2/27/2017 2:24:00 PM",
    "foundTimestamp": 1564057289126
  },
  "CP-20-CR-0000195-2017": {
    "assignmentID": "cp0h2h09check4",
    "position": {
      "index": 13,
      "page": 10
    },
    "id": "CP-20-CR-0000195-2017",
    "filingDate": "2/27/2017 8:39:00 AM",
    "foundTimestamp": 1564057289205
  },
  "CP-23-CR-0000755-2017": {
    "assignmentID": "cp0h2h09check4",
    "position": {
      "index": 13,
      "page": 10
    },
    "id": "CP-23-CR-0000755-2017",
    "filingDate": "2/8/2017 12:27:00 PM",
    "foundTimestamp": 1564057289208
  },
  "CP-02-CR-0001304-2017": {
    "assignmentID": "cp0h2h09check4",
    "position": {
      "index": 13,
      "page": 10
    },
    "id": "CP-02-CR-0001304-2017",
    "filingDate": "2/3/2017 1:06:00 PM",
    "foundTimestamp": 1564057289288
  },
  "CP-26-CR-0000185-2017": {
    "assignmentID": "cp0h2h09check4",
    "position": {
      "index": 13,
      "page": 10
    },
    "id": "CP-26-CR-0000185-2017",
    "filingDate": "2/1/2017 3:49:00 PM",
    "foundTimestamp": 1564057289333
  },
  "CP-09-CR-0000426-2017": {
    "assignmentID": "cp0h2h09check4",
    "position": {
      "index": 13,
      "page": 10
    },
    "id": "CP-09-CR-0000426-2017",
    "filingDate": "1/23/2017 11:07:00 AM",
    "foundTimestamp": 1564057289374
  },
  "CP-13-CR-0000093-2017": {
    "assignmentID": "cp0h2h09check4",
    "position": {
      "index": 13,
      "page": 10
    },
    "id": "CP-13-CR-0000093-2017",
    "filingDate": "1/20/2017 2:23:00 PM",
    "foundTimestamp": 1564057289454
  },
  "CP-02-CR-0000229-2017": {
    "assignmentID": "cp0h2h09check4",
    "position": {
      "index": 13,
      "page": 10
    },
    "id": "CP-02-CR-0000229-2017",
    "filingDate": "1/10/2017 3:22:00 PM",
    "foundTimestamp": 1564057289495
  },
  "CP-07-CR-0000047-2017": {
    "assignmentID": "cp0h2h09check4",
    "position": {
      "index": 13,
      "page": 10
    },
    "id": "CP-07-CR-0000047-2017",
    "filingDate": "1/10/2017 10:30:00 AM",
    "foundTimestamp": 1564057289537
  },
  "CP-02-CR-0000123-2017": {
    "assignmentID": "cp0h2h09check4",
    "position": {
      "index": 13,
      "page": 10
    },
    "id": "CP-02-CR-0000123-2017",
    "filingDate": "1/6/2017 3:28:00 PM",
    "foundTimestamp": 1564057289577
  },
  "CP-23-CR-0007807-2016": {
    "assignmentID": "cp0h2h09check4",
    "position": {
      "index": 13,
      "page": 11
    },
    "id": "CP-23-CR-0007807-2016",
    "filingDate": "12/19/2016 9:40:00 AM",
    "foundTimestamp": 1564057316199
  },
  "CP-45-CR-0002632-2016": {
    "assignmentID": "cp0h2h09check4",
    "position": {
      "index": 13,
      "page": 11
    },
    "id": "CP-45-CR-0002632-2016",
    "filingDate": "12/1/2016 1:04:00 PM",
    "foundTimestamp": 1564057316321
  },
  "CP-26-CR-0002227-2016": {
    "assignmentID": "cp0h2h09check4",
    "position": {
      "index": 13,
      "page": 11
    },
    "id": "CP-26-CR-0002227-2016",
    "filingDate": "11/21/2016 4:08:00 PM",
    "foundTimestamp": 1564057316402
  },
  "CP-40-CR-0004195-2016": {
    "assignmentID": "cp0h2h09check4",
    "position": {
      "index": 13,
      "page": 11
    },
    "id": "CP-40-CR-0004195-2016",
    "filingDate": "11/15/2016 2:36:00 PM",
    "foundTimestamp": 1564057316483
  },
  "CP-45-CR-0002399-2016": {
    "assignmentID": "cp0h2h09check4",
    "position": {
      "index": 13,
      "page": 11
    },
    "id": "CP-45-CR-0002399-2016",
    "filingDate": "11/3/2016 1:56:00 PM",
    "foundTimestamp": 1564057316564
  },
  "CP-31-CR-0000609-2016": {
    "assignmentID": "cp0h2h09check4",
    "position": {
      "index": 13,
      "page": 11
    },
    "id": "CP-31-CR-0000609-2016",
    "filingDate": "10/12/2016 12:50:00 PM",
    "foundTimestamp": 1564057316645
  },
  "CP-36-CR-0004765-2016": {
    "assignmentID": "cp0h2h09check4",
    "position": {
      "index": 13,
      "page": 11
    },
    "id": "CP-36-CR-0004765-2016",
    "filingDate": "9/22/2016 9:32:00 AM",
    "foundTimestamp": 1564057316686
  },
  "CP-67-CR-0005911-2016": {
    "assignmentID": "cp0h2h09check4",
    "position": {
      "index": 13,
      "page": 11
    },
    "id": "CP-67-CR-0005911-2016",
    "filingDate": "9/12/2016 3:13:00 PM",
    "foundTimestamp": 1564057316890
  },
  "CP-23-CR-0004200-2016": {
    "assignmentID": "cp0h2h09check4",
    "position": {
      "index": 13,
      "page": 12
    },
    "id": "CP-23-CR-0004200-2016",
    "filingDate": "7/11/2016 10:56:00 AM",
    "foundTimestamp": 1564057338067
  },
  "CP-67-CR-0003572-2016": {
    "assignmentID": "cp0h2h09check4",
    "position": {
      "index": 13,
      "page": 12
    },
    "id": "CP-67-CR-0003572-2016",
    "filingDate": "6/1/2016 1:43:00 PM",
    "foundTimestamp": 1564057338108
  },
  "CP-39-CR-0002225-2016": {
    "assignmentID": "cp0h2h09check4",
    "position": {
      "index": 13,
      "page": 12
    },
    "id": "CP-39-CR-0002225-2016",
    "filingDate": "5/24/2016 9:29:00 AM",
    "foundTimestamp": 1564057338148
  },
  "CP-23-CR-0002574-2016": {
    "assignmentID": "cp0h2h09check4",
    "position": {
      "index": 13,
      "page": 12
    },
    "id": "CP-23-CR-0002574-2016",
    "filingDate": "5/2/2016 12:27:00 PM",
    "foundTimestamp": 1564057338190
  },
  "CP-39-CR-0001759-2016": {
    "assignmentID": "cp0h2h09check4",
    "position": {
      "index": 13,
      "page": 12
    },
    "id": "CP-39-CR-0001759-2016",
    "filingDate": "4/21/2016 1:31:00 PM",
    "foundTimestamp": 1564057338231
  },
  "CP-65-CR-0001476-2016": {
    "assignmentID": "cp0h2h09check4",
    "position": {
      "index": 13,
      "page": 12
    },
    "id": "CP-65-CR-0001476-2016",
    "filingDate": "3/31/2016 9:23:00 AM",
    "foundTimestamp": 1564057338350
  },
  "CP-65-CR-0001214-2016": {
    "assignmentID": "cp0h2h09check4",
    "position": {
      "index": 13,
      "page": 12
    },
    "id": "CP-65-CR-0001214-2016",
    "filingDate": "3/15/2016 11:17:00 AM",
    "foundTimestamp": 1564057338352
  },
  "CP-22-CR-0001403-2016": {
    "assignmentID": "cp0h2h09check4",
    "position": {
      "index": 13,
      "page": 12
    },
    "id": "CP-22-CR-0001403-2016",
    "filingDate": "3/14/2016 1:21:00 PM",
    "foundTimestamp": 1564057338392
  }
}